{
  "scan_scope": {
    "p_values": [
      2,
      3,
      4,
      5
    ],
    "k_values": [
      1,
      2,
      3
    ],
    "group_count": 11,
    "total_family_count": 6336
  },
  "current_semantics": {
    "all_factorization_checks_passed": true,
    "total_collapse_failures": 0,
    "groups": [
      {
        "p": 2,
        "k": 1,
        "family_count": 1,
        "factorization_holds": true,
        "collapse_failures": 0,
        "family_row_count": 5,
        "family_bits": 2.321928094887362,
        "answer_count_range": [
          3,
          3
        ],
        "answer_bit_range": [
          1.584962500721156,
          1.584962500721156
        ],
        "shelf_width_range_bits": [
          0.7369655941662061,
          0.7369655941662061
        ],
        "min_answer_examples": [
          {
            "family": [
              [
                1
              ],
              [
                2
              ]
            ],
            "family_size": 2,
            "core_size": 0,
            "hitting_number": 2,
            "symmetry_group_size": 2,
            "pairwise_intersections": [
              0
            ],
            "answer_row_count": 3,
            "shelf_width_bits": 0.736966
          }
        ],
        "max_answer_examples": [
          {
            "family": [
              [
                1
              ],
              [
                2
              ]
            ],
            "family_size": 2,
            "core_size": 0,
            "hitting_number": 2,
            "symmetry_group_size": 2,
            "pairwise_intersections": [
              0
            ],
            "answer_row_count": 3,
            "shelf_width_bits": 0.736966
          }
        ]
      },
      {
        "p": 2,
        "k": 2,
        "family_count": 1,
        "factorization_holds": true,
        "collapse_failures": 0,
        "family_row_count": 6,
        "family_bits": 2.584962500721156,
        "answer_count_range": [
          6,
          6
        ],
        "answer_bit_range": [
          2.584962500721156,
          2.584962500721156
        ],
        "shelf_width_range_bits": [
          0.0,
          0.0
        ],
        "min_answer_examples": [
          {
            "family": [
              [
                1,
                2
              ]
            ],
            "family_size": 1,
            "core_size": 2,
            "hitting_number": 1,
            "symmetry_group_size": 2,
            "pairwise_intersections": [],
            "answer_row_count": 6,
            "shelf_width_bits": 0.0
          }
        ],
        "max_answer_examples": [
          {
            "family": [
              [
                1,
                2
              ]
            ],
            "family_size": 1,
            "core_size": 2,
            "hitting_number": 1,
            "symmetry_group_size": 2,
            "pairwise_intersections": [],
            "answer_row_count": 6,
            "shelf_width_bits": 0.0
          }
        ]
      },
      {
        "p": 3,
        "k": 1,
        "family_count": 1,
        "factorization_holds": true,
        "collapse_failures": 0,
        "family_row_count": 9,
        "family_bits": 3.169925001442312,
        "answer_count_range": [
          3,
          3
        ],
        "answer_bit_range": [
          1.584962500721156,
          1.584962500721156
        ],
        "shelf_width_range_bits": [
          1.584962500721156,
          1.584962500721156
        ],
        "min_answer_examples": [
          {
            "family": [
              [
                1
              ],
              [
                2
              ],
              [
                3
              ]
            ],
            "family_size": 3,
            "core_size": 0,
            "hitting_number": 3,
            "symmetry_group_size": 6,
            "pairwise_intersections": [
              0,
              0,
              0
            ],
            "answer_row_count": 3,
            "shelf_width_bits": 1.584963
          }
        ],
        "max_answer_examples": [
          {
            "family": [
              [
                1
              ],
              [
                2
              ],
              [
                3
              ]
            ],
            "family_size": 3,
            "core_size": 0,
            "hitting_number": 3,
            "symmetry_group_size": 6,
            "pairwise_intersections": [
              0,
              0,
              0
            ],
            "answer_row_count": 3,
            "shelf_width_bits": 1.584963
          }
        ]
      },
      {
        "p": 3,
        "k": 2,
        "family_count": 7,
        "factorization_holds": true,
        "collapse_failures": 0,
        "family_row_count": 10,
        "family_bits": 3.321928094887362,
        "answer_count_range": [
          6,
          7
        ],
        "answer_bit_range": [
          2.584962500721156,
          2.807354922057604
        ],
        "shelf_width_range_bits": [
          0.514573172829758,
          0.7369655941662061
        ],
        "min_answer_examples": [
          {
            "family": [
              [
                1,
                3
              ],
              [
                2,
                3
              ]
            ],
            "family_size": 2,
            "core_size": 1,
            "hitting_number": 1,
            "symmetry_group_size": 2,
            "pairwise_intersections": [
              1
            ],
            "answer_row_count": 6,
            "shelf_width_bits": 0.736966
          },
          {
            "family": [
              [
                1,
                2
              ],
              [
                2,
                3
              ]
            ],
            "family_size": 2,
            "core_size": 1,
            "hitting_number": 1,
            "symmetry_group_size": 2,
            "pairwise_intersections": [
              1
            ],
            "answer_row_count": 6,
            "shelf_width_bits": 0.736966
          },
          {
            "family": [
              [
                1,
                2
              ],
              [
                1,
                3
              ]
            ],
            "family_size": 2,
            "core_size": 1,
            "hitting_number": 1,
            "symmetry_group_size": 2,
            "pairwise_intersections": [
              1
            ],
            "answer_row_count": 6,
            "shelf_width_bits": 0.736966
          }
        ],
        "max_answer_examples": [
          {
            "family": [
              [
                1,
                2
              ],
              [
                1,
                3
              ],
              [
                2,
                3
              ]
            ],
            "family_size": 3,
            "core_size": 0,
            "hitting_number": 2,
            "symmetry_group_size": 6,
            "pairwise_intersections": [
              1,
              1,
              1
            ],
            "answer_row_count": 7,
            "shelf_width_bits": 0.514573
          }
        ]
      },
      {
        "p": 3,
        "k": 3,
        "family_count": 1,
        "factorization_holds": true,
        "collapse_failures": 0,
        "family_row_count": 11,
        "family_bits": 3.4594316186372973,
        "answer_count_range": [
          11,
          11
        ],
        "answer_bit_range": [
          3.4594316186372973,
          3.4594316186372973
        ],
        "shelf_width_range_bits": [
          0.0,
          0.0
        ],
        "min_answer_examples": [
          {
            "family": [
              [
                1,
                2,
                3
              ]
            ],
            "family_size": 1,
            "core_size": 3,
            "hitting_number": 1,
            "symmetry_group_size": 6,
            "pairwise_intersections": [],
            "answer_row_count": 11,
            "shelf_width_bits": 0.0
          }
        ],
        "max_answer_examples": [
          {
            "family": [
              [
                1,
                2,
                3
              ]
            ],
            "family_size": 1,
            "core_size": 3,
            "hitting_number": 1,
            "symmetry_group_size": 6,
            "pairwise_intersections": [],
            "answer_row_count": 11,
            "shelf_width_bits": 0.0
          }
        ]
      },
      {
        "p": 4,
        "k": 1,
        "family_count": 1,
        "factorization_holds": true,
        "collapse_failures": 0,
        "family_row_count": 17,
        "family_bits": 4.087462841250339,
        "answer_count_range": [
          3,
          3
        ],
        "answer_bit_range": [
          1.584962500721156,
          1.584962500721156
        ],
        "shelf_width_range_bits": [
          2.502500340529183,
          2.502500340529183
        ],
        "min_answer_examples": [
          {
            "family": [
              [
                1
              ],
              [
                2
              ],
              [
                3
              ],
              [
                4
              ]
            ],
            "family_size": 4,
            "core_size": 0,
            "hitting_number": 4,
            "symmetry_group_size": 24,
            "pairwise_intersections": [
              0,
              0,
              0,
              0,
              0,
              0
            ],
            "answer_row_count": 3,
            "shelf_width_bits": 2.5025
          }
        ],
        "max_answer_examples": [
          {
            "family": [
              [
                1
              ],
              [
                2
              ],
              [
                3
              ],
              [
                4
              ]
            ],
            "family_size": 4,
            "core_size": 0,
            "hitting_number": 4,
            "symmetry_group_size": 24,
            "pairwise_intersections": [
              0,
              0,
              0,
              0,
              0,
              0
            ],
            "answer_row_count": 3,
            "shelf_width_bits": 2.5025
          }
        ]
      },
      {
        "p": 4,
        "k": 2,
        "family_count": 63,
        "factorization_holds": true,
        "collapse_failures": 0,
        "family_row_count": 18,
        "family_bits": 4.169925001442312,
        "answer_count_range": [
          6,
          12
        ],
        "answer_bit_range": [
          2.584962500721156,
          3.584962500721156
        ],
        "shelf_width_range_bits": [
          0.5849625007211561,
          1.584962500721156
        ],
        "min_answer_examples": [
          {
            "family": [
              [
                1,
                4
              ],
              [
                2,
                4
              ],
              [
                3,
                4
              ]
            ],
            "family_size": 3,
            "core_size": 1,
            "hitting_number": 1,
            "symmetry_group_size": 6,
            "pairwise_intersections": [
              1,
              1,
              1
            ],
            "answer_row_count": 6,
            "shelf_width_bits": 1.584963
          },
          {
            "family": [
              [
                1,
                3
              ],
              [
                2,
                3
              ],
              [
                3,
                4
              ]
            ],
            "family_size": 3,
            "core_size": 1,
            "hitting_number": 1,
            "symmetry_group_size": 6,
            "pairwise_intersections": [
              1,
              1,
              1
            ],
            "answer_row_count": 6,
            "shelf_width_bits": 1.584963
          },
          {
            "family": [
              [
                1,
                3
              ],
              [
                1,
                4
              ],
              [
                2,
                3
              ],
              [
                2,
                4
              ]
            ],
            "family_size": 4,
            "core_size": 0,
            "hitting_number": 2,
            "symmetry_group_size": 8,
            "pairwise_intersections": [
              0,
              0,
              1,
              1,
              1,
              1
            ],
            "answer_row_count": 6,
            "shelf_width_bits": 1.584963
          }
        ],
        "max_answer_examples": [
          {
            "family": [
              [
                1,
                4
              ],
              [
                2,
                3
              ]
            ],
            "family_size": 2,
            "core_size": 0,
            "hitting_number": 2,
            "symmetry_group_size": 8,
            "pairwise_intersections": [
              0
            ],
            "answer_row_count": 12,
            "shelf_width_bits": 0.584963
          },
          {
            "family": [
              [
                1,
                3
              ],
              [
                2,
                4
              ]
            ],
            "family_size": 2,
            "core_size": 0,
            "hitting_number": 2,
            "symmetry_group_size": 8,
            "pairwise_intersections": [
              0
            ],
            "answer_row_count": 12,
            "shelf_width_bits": 0.584963
          },
          {
            "family": [
              [
                1,
                2
              ],
              [
                3,
                4
              ]
            ],
            "family_size": 2,
            "core_size": 0,
            "hitting_number": 2,
            "symmetry_group_size": 8,
            "pairwise_intersections": [
              0
            ],
            "answer_row_count": 12,
            "shelf_width_bits": 0.584963
          }
        ]
      },
      {
        "p": 4,
        "k": 3,
        "family_count": 49,
        "factorization_holds": true,
        "collapse_failures": 0,
        "family_row_count": 19,
        "family_bits": 4.247927513443585,
        "answer_count_range": [
          11,
          15
        ],
        "answer_bit_range": [
          3.4594316186372973,
          3.9068905956085187
        ],
        "shelf_width_range_bits": [
          0.3410369178350665,
          0.7884958948062879
        ],
        "min_answer_examples": [
          {
            "family": [
              [
                1,
                3,
                4
              ],
              [
                2,
                3,
                4
              ]
            ],
            "family_size": 2,
            "core_size": 2,
            "hitting_number": 1,
            "symmetry_group_size": 4,
            "pairwise_intersections": [
              2
            ],
            "answer_row_count": 11,
            "shelf_width_bits": 0.788496
          },
          {
            "family": [
              [
                1,
                2,
                4
              ],
              [
                2,
                3,
                4
              ]
            ],
            "family_size": 2,
            "core_size": 2,
            "hitting_number": 1,
            "symmetry_group_size": 4,
            "pairwise_intersections": [
              2
            ],
            "answer_row_count": 11,
            "shelf_width_bits": 0.788496
          },
          {
            "family": [
              [
                1,
                2,
                4
              ],
              [
                1,
                3,
                4
              ]
            ],
            "family_size": 2,
            "core_size": 2,
            "hitting_number": 1,
            "symmetry_group_size": 4,
            "pairwise_intersections": [
              2
            ],
            "answer_row_count": 11,
            "shelf_width_bits": 0.788496
          }
        ],
        "max_answer_examples": [
          {
            "family": [
              [
                1,
                2,
                3
              ],
              [
                1,
                2,
                4
              ],
              [
                1,
                3,
                4
              ],
              [
                2,
                3,
                4
              ]
            ],
            "family_size": 4,
            "core_size": 0,
            "hitting_number": 2,
            "symmetry_group_size": 24,
            "pairwise_intersections": [
              2,
              2,
              2,
              2,
              2,
              2
            ],
            "answer_row_count": 15,
            "shelf_width_bits": 0.341037
          }
        ]
      },
      {
        "p": 5,
        "k": 1,
        "family_count": 1,
        "factorization_holds": true,
        "collapse_failures": 0,
        "family_row_count": 33,
        "family_bits": 5.044394119358453,
        "answer_count_range": [
          3,
          3
        ],
        "answer_bit_range": [
          1.584962500721156,
          1.584962500721156
        ],
        "shelf_width_range_bits": [
          3.4594316186372973,
          3.4594316186372973
        ],
        "min_answer_examples": [
          {
            "family": [
              [
                1
              ],
              [
                2
              ],
              [
                3
              ],
              [
                4
              ],
              [
                5
              ]
            ],
            "family_size": 5,
            "core_size": 0,
            "hitting_number": 5,
            "symmetry_group_size": 120,
            "pairwise_intersections": [
              0,
              0,
              0,
              0,
              0,
              0,
              0,
              0,
              0,
              0
            ],
            "answer_row_count": 3,
            "shelf_width_bits": 3.459432
          }
        ],
        "max_answer_examples": [
          {
            "family": [
              [
                1
              ],
              [
                2
              ],
              [
                3
              ],
              [
                4
              ],
              [
                5
              ]
            ],
            "family_size": 5,
            "core_size": 0,
            "hitting_number": 5,
            "symmetry_group_size": 120,
            "pairwise_intersections": [
              0,
              0,
              0,
              0,
              0,
              0,
              0,
              0,
              0,
              0
            ],
            "answer_row_count": 3,
            "shelf_width_bits": 3.459432
          }
        ]
      },
      {
        "p": 5,
        "k": 2,
        "family_count": 1023,
        "factorization_holds": true,
        "collapse_failures": 0,
        "family_row_count": 34,
        "family_bits": 5.087462841250339,
        "answer_count_range": [
          6,
          15
        ],
        "answer_bit_range": [
          2.584962500721156,
          3.9068905956085187
        ],
        "shelf_width_range_bits": [
          1.1805722456418204,
          2.502500340529183
        ],
        "min_answer_examples": [
          {
            "family": [
              [
                1,
                5
              ],
              [
                2,
                5
              ],
              [
                3,
                5
              ],
              [
                4,
                5
              ]
            ],
            "family_size": 4,
            "core_size": 1,
            "hitting_number": 1,
            "symmetry_group_size": 24,
            "pairwise_intersections": [
              1,
              1,
              1,
              1,
              1,
              1
            ],
            "answer_row_count": 6,
            "shelf_width_bits": 2.5025
          },
          {
            "family": [
              [
                1,
                4
              ],
              [
                2,
                4
              ],
              [
                3,
                4
              ],
              [
                4,
                5
              ]
            ],
            "family_size": 4,
            "core_size": 1,
            "hitting_number": 1,
            "symmetry_group_size": 24,
            "pairwise_intersections": [
              1,
              1,
              1,
              1,
              1,
              1
            ],
            "answer_row_count": 6,
            "shelf_width_bits": 2.5025
          },
          {
            "family": [
              [
                1,
                4
              ],
              [
                1,
                5
              ],
              [
                2,
                4
              ],
              [
                2,
                5
              ],
              [
                3,
                4
              ],
              [
                3,
                5
              ]
            ],
            "family_size": 6,
            "core_size": 0,
            "hitting_number": 2,
            "symmetry_group_size": 12,
            "pairwise_intersections": [
              0,
              0,
              0,
              0,
              0,
              0,
              1,
              1,
              1,
              1,
              1,
              1,
              1,
              1,
              1
            ],
            "answer_row_count": 6,
            "shelf_width_bits": 2.5025
          }
        ],
        "max_answer_examples": [
          {
            "family": [
              [
                1,
                5
              ],
              [
                2,
                3
              ],
              [
                2,
                4
              ],
              [
                3,
                4
              ]
            ],
            "family_size": 4,
            "core_size": 0,
            "hitting_number": 3,
            "symmetry_group_size": 12,
            "pairwise_intersections": [
              0,
              0,
              0,
              1,
              1,
              1
            ],
            "answer_row_count": 15,
            "shelf_width_bits": 1.180572
          },
          {
            "family": [
              [
                1,
                4
              ],
              [
                2,
                3
              ],
              [
                2,
                5
              ],
              [
                3,
                5
              ]
            ],
            "family_size": 4,
            "core_size": 0,
            "hitting_number": 3,
            "symmetry_group_size": 12,
            "pairwise_intersections": [
              0,
              0,
              0,
              1,
              1,
              1
            ],
            "answer_row_count": 15,
            "shelf_width_bits": 1.180572
          },
          {
            "family": [
              [
                1,
                4
              ],
              [
                1,
                5
              ],
              [
                2,
                3
              ],
              [
                4,
                5
              ]
            ],
            "family_size": 4,
            "core_size": 0,
            "hitting_number": 3,
            "symmetry_group_size": 12,
            "pairwise_intersections": [
              0,
              0,
              0,
              1,
              1,
              1
            ],
            "answer_row_count": 15,
            "shelf_width_bits": 1.180572
          }
        ]
      },
      {
        "p": 5,
        "k": 3,
        "family_count": 5188,
        "factorization_holds": true,
        "collapse_failures": 0,
        "family_row_count": 35,
        "family_bits": 5.129283016944966,
        "answer_count_range": [
          11,
          26
        ],
        "answer_bit_range": [
          3.4594316186372973,
          4.700439718141092
        ],
        "shelf_width_range_bits": [
          0.4288432988038746,
          1.669851398307669
        ],
        "min_answer_examples": [
          {
            "family": [
              [
                1,
                4,
                5
              ],
              [
                2,
                4,
                5
              ],
              [
                3,
                4,
                5
              ]
            ],
            "family_size": 3,
            "core_size": 2,
            "hitting_number": 1,
            "symmetry_group_size": 12,
            "pairwise_intersections": [
              2,
              2,
              2
            ],
            "answer_row_count": 11,
            "shelf_width_bits": 1.669851
          },
          {
            "family": [
              [
                1,
                3,
                5
              ],
              [
                2,
                3,
                5
              ],
              [
                3,
                4,
                5
              ]
            ],
            "family_size": 3,
            "core_size": 2,
            "hitting_number": 1,
            "symmetry_group_size": 12,
            "pairwise_intersections": [
              2,
              2,
              2
            ],
            "answer_row_count": 11,
            "shelf_width_bits": 1.669851
          },
          {
            "family": [
              [
                1,
                3,
                5
              ],
              [
                1,
                4,
                5
              ],
              [
                2,
                3,
                5
              ],
              [
                2,
                4,
                5
              ]
            ],
            "family_size": 4,
            "core_size": 1,
            "hitting_number": 1,
            "symmetry_group_size": 8,
            "pairwise_intersections": [
              1,
              1,
              2,
              2,
              2,
              2
            ],
            "answer_row_count": 11,
            "shelf_width_bits": 1.669851
          }
        ],
        "max_answer_examples": [
          {
            "family": [
              [
                1,
                4,
                5
              ],
              [
                2,
                3,
                4
              ],
              [
                2,
                3,
                5
              ]
            ],
            "family_size": 3,
            "core_size": 0,
            "hitting_number": 2,
            "symmetry_group_size": 4,
            "pairwise_intersections": [
              1,
              1,
              2
            ],
            "answer_row_count": 26,
            "shelf_width_bits": 0.428843
          },
          {
            "family": [
              [
                1,
                3,
                5
              ],
              [
                2,
                3,
                4
              ],
              [
                2,
                4,
                5
              ]
            ],
            "family_size": 3,
            "core_size": 0,
            "hitting_number": 2,
            "symmetry_group_size": 4,
            "pairwise_intersections": [
              1,
              1,
              2
            ],
            "answer_row_count": 26,
            "shelf_width_bits": 0.428843
          },
          {
            "family": [
              [
                1,
                3,
                5
              ],
              [
                1,
                4,
                5
              ],
              [
                2,
                3,
                4
              ]
            ],
            "family_size": 3,
            "core_size": 0,
            "hitting_number": 2,
            "symmetry_group_size": 4,
            "pairwise_intersections": [
              1,
              1,
              2
            ],
            "answer_row_count": 26,
            "shelf_width_bits": 0.428843
          }
        ]
      }
    ],
    "contract_candidates_by_group": {
      "(p=2, k=1)": {
        "union_core_size": {
          "summary_count": 1,
          "mixed_classes": 0,
          "exact": true
        },
        "degree_signature": {
          "summary_count": 1,
          "mixed_classes": 0,
          "exact": true
        },
        "intersection_signature": {
          "summary_count": 1,
          "mixed_classes": 0,
          "exact": true
        },
        "orbit": {
          "summary_count": 1,
          "mixed_classes": 0,
          "exact": true
        },
        "full_antichain": {
          "summary_count": 1,
          "mixed_classes": 0,
          "exact": true
        }
      },
      "(p=2, k=2)": {
        "union_core_size": {
          "summary_count": 1,
          "mixed_classes": 0,
          "exact": true
        },
        "degree_signature": {
          "summary_count": 1,
          "mixed_classes": 0,
          "exact": true
        },
        "intersection_signature": {
          "summary_count": 1,
          "mixed_classes": 0,
          "exact": true
        },
        "orbit": {
          "summary_count": 1,
          "mixed_classes": 0,
          "exact": true
        },
        "full_antichain": {
          "summary_count": 1,
          "mixed_classes": 0,
          "exact": true
        }
      },
      "(p=3, k=1)": {
        "union_core_size": {
          "summary_count": 1,
          "mixed_classes": 0,
          "exact": true
        },
        "degree_signature": {
          "summary_count": 1,
          "mixed_classes": 0,
          "exact": true
        },
        "intersection_signature": {
          "summary_count": 1,
          "mixed_classes": 0,
          "exact": true
        },
        "orbit": {
          "summary_count": 1,
          "mixed_classes": 0,
          "exact": true
        },
        "full_antichain": {
          "summary_count": 1,
          "mixed_classes": 0,
          "exact": true
        }
      },
      "(p=3, k=2)": {
        "union_core_size": {
          "summary_count": 5,
          "mixed_classes": 1,
          "exact": false
        },
        "degree_signature": {
          "summary_count": 3,
          "mixed_classes": 2,
          "exact": false
        },
        "intersection_signature": {
          "summary_count": 3,
          "mixed_classes": 2,
          "exact": false
        },
        "orbit": {
          "summary_count": 3,
          "mixed_classes": 2,
          "exact": false
        },
        "full_antichain": {
          "summary_count": 7,
          "mixed_classes": 0,
          "exact": true
        }
      },
      "(p=3, k=3)": {
        "union_core_size": {
          "summary_count": 1,
          "mixed_classes": 0,
          "exact": true
        },
        "degree_signature": {
          "summary_count": 1,
          "mixed_classes": 0,
          "exact": true
        },
        "intersection_signature": {
          "summary_count": 1,
          "mixed_classes": 0,
          "exact": true
        },
        "orbit": {
          "summary_count": 1,
          "mixed_classes": 0,
          "exact": true
        },
        "full_antichain": {
          "summary_count": 1,
          "mixed_classes": 0,
          "exact": true
        }
      },
      "(p=4, k=1)": {
        "union_core_size": {
          "summary_count": 1,
          "mixed_classes": 0,
          "exact": true
        },
        "degree_signature": {
          "summary_count": 1,
          "mixed_classes": 0,
          "exact": true
        },
        "intersection_signature": {
          "summary_count": 1,
          "mixed_classes": 0,
          "exact": true
        },
        "orbit": {
          "summary_count": 1,
          "mixed_classes": 0,
          "exact": true
        },
        "full_antichain": {
          "summary_count": 1,
          "mixed_classes": 0,
          "exact": true
        }
      },
      "(p=4, k=2)": {
        "union_core_size": {
          "summary_count": 12,
          "mixed_classes": 7,
          "exact": false
        },
        "degree_signature": {
          "summary_count": 10,
          "mixed_classes": 9,
          "exact": false
        },
        "intersection_signature": {
          "summary_count": 10,
          "mixed_classes": 9,
          "exact": false
        },
        "orbit": {
          "summary_count": 10,
          "mixed_classes": 9,
          "exact": false
        },
        "full_antichain": {
          "summary_count": 63,
          "mixed_classes": 0,
          "exact": true
        }
      },
      "(p=4, k=3)": {
        "union_core_size": {
          "summary_count": 19,
          "mixed_classes": 8,
          "exact": false
        },
        "degree_signature": {
          "summary_count": 8,
          "mixed_classes": 7,
          "exact": false
        },
        "intersection_signature": {
          "summary_count": 8,
          "mixed_classes": 7,
          "exact": false
        },
        "orbit": {
          "summary_count": 8,
          "mixed_classes": 7,
          "exact": false
        },
        "full_antichain": {
          "summary_count": 49,
          "mixed_classes": 0,
          "exact": true
        }
      },
      "(p=5, k=1)": {
        "union_core_size": {
          "summary_count": 1,
          "mixed_classes": 0,
          "exact": true
        },
        "degree_signature": {
          "summary_count": 1,
          "mixed_classes": 0,
          "exact": true
        },
        "intersection_signature": {
          "summary_count": 1,
          "mixed_classes": 0,
          "exact": true
        },
        "orbit": {
          "summary_count": 1,
          "mixed_classes": 0,
          "exact": true
        },
        "full_antichain": {
          "summary_count": 1,
          "mixed_classes": 0,
          "exact": true
        }
      },
      "(p=5, k=2)": {
        "union_core_size": {
          "summary_count": 21,
          "mixed_classes": 15,
          "exact": false
        },
        "degree_signature": {
          "summary_count": 30,
          "mixed_classes": 29,
          "exact": false
        },
        "intersection_signature": {
          "summary_count": 28,
          "mixed_classes": 27,
          "exact": false
        },
        "orbit": {
          "summary_count": 33,
          "mixed_classes": 32,
          "exact": false
        },
        "full_antichain": {
          "summary_count": 1023,
          "mixed_classes": 0,
          "exact": true
        }
      },
      "(p=5, k=3)": {
        "union_core_size": {
          "summary_count": 90,
          "mixed_classes": 74,
          "exact": false
        },
        "degree_signature": {
          "summary_count": 80,
          "mixed_classes": 79,
          "exact": false
        },
        "intersection_signature": {
          "summary_count": 88,
          "mixed_classes": 87,
          "exact": false
        },
        "orbit": {
          "summary_count": 117,
          "mixed_classes": 116,
          "exact": false
        },
        "full_antichain": {
          "summary_count": 5188,
          "mixed_classes": 0,
          "exact": true
        }
      }
    }
  },
  "teaching_complexity": {
    "groups": [
      {
        "p": 2,
        "k": 1,
        "family_count": 1,
        "answer_basis_size": 0,
        "variable_basis_size": 0,
        "family_basis_size": 0,
        "answer_basis_exact": true,
        "answer_basis_essential": false,
        "variable_basis_exact": true,
        "variable_basis_essential": false,
        "family_basis_exact": true,
        "answer_basis_example": [],
        "variable_basis_example": [],
        "family_basis_example": []
      },
      {
        "p": 2,
        "k": 2,
        "family_count": 1,
        "answer_basis_size": 0,
        "variable_basis_size": 0,
        "family_basis_size": 0,
        "answer_basis_exact": true,
        "answer_basis_essential": false,
        "variable_basis_exact": true,
        "variable_basis_essential": false,
        "family_basis_exact": true,
        "answer_basis_example": [],
        "variable_basis_example": [],
        "family_basis_example": []
      },
      {
        "p": 3,
        "k": 1,
        "family_count": 1,
        "answer_basis_size": 0,
        "variable_basis_size": 0,
        "family_basis_size": 0,
        "answer_basis_exact": true,
        "answer_basis_essential": false,
        "variable_basis_exact": true,
        "variable_basis_essential": false,
        "family_basis_exact": true,
        "answer_basis_example": [],
        "variable_basis_example": [],
        "family_basis_example": []
      },
      {
        "p": 3,
        "k": 2,
        "family_count": 7,
        "answer_basis_size": 6,
        "variable_basis_size": 3,
        "family_basis_size": 1,
        "answer_basis_exact": true,
        "answer_basis_essential": true,
        "variable_basis_exact": true,
        "variable_basis_essential": true,
        "family_basis_exact": true,
        "answer_basis_example": [
          [
            1
          ],
          [
            2
          ],
          [
            3
          ],
          [
            1,
            2
          ],
          [
            1,
            3
          ],
          [
            2,
            3
          ]
        ],
        "variable_basis_example": [
          [
            1,
            2
          ],
          [
            1,
            3
          ],
          [
            2,
            3
          ]
        ],
        "family_basis_example": [
          [
            1,
            2,
            3
          ]
        ]
      },
      {
        "p": 3,
        "k": 3,
        "family_count": 1,
        "answer_basis_size": 0,
        "variable_basis_size": 0,
        "family_basis_size": 0,
        "answer_basis_exact": true,
        "answer_basis_essential": false,
        "variable_basis_exact": true,
        "variable_basis_essential": false,
        "family_basis_exact": true,
        "answer_basis_example": [],
        "variable_basis_example": [],
        "family_basis_example": []
      },
      {
        "p": 4,
        "k": 1,
        "family_count": 1,
        "answer_basis_size": 0,
        "variable_basis_size": 0,
        "family_basis_size": 0,
        "answer_basis_exact": true,
        "answer_basis_essential": false,
        "variable_basis_exact": true,
        "variable_basis_essential": false,
        "family_basis_exact": true,
        "answer_basis_example": [],
        "variable_basis_example": [],
        "family_basis_example": []
      },
      {
        "p": 4,
        "k": 2,
        "family_count": 63,
        "answer_basis_size": 10,
        "variable_basis_size": 6,
        "family_basis_size": 1,
        "answer_basis_exact": true,
        "answer_basis_essential": true,
        "variable_basis_exact": true,
        "variable_basis_essential": true,
        "family_basis_exact": true,
        "answer_basis_example": [
          [
            1
          ],
          [
            2
          ],
          [
            3
          ],
          [
            4
          ],
          [
            1,
            2
          ],
          [
            1,
            3
          ]
        ],
        "variable_basis_example": [
          [
            1,
            2
          ],
          [
            1,
            3
          ],
          [
            1,
            4
          ],
          [
            2,
            3
          ],
          [
            2,
            4
          ],
          [
            3,
            4
          ]
        ],
        "family_basis_example": [
          [
            1,
            2,
            3,
            4
          ]
        ]
      },
      {
        "p": 4,
        "k": 3,
        "family_count": 49,
        "answer_basis_size": 14,
        "variable_basis_size": 7,
        "family_basis_size": 1,
        "answer_basis_exact": true,
        "answer_basis_essential": true,
        "variable_basis_exact": true,
        "variable_basis_essential": true,
        "family_basis_exact": true,
        "answer_basis_example": [
          [
            1
          ],
          [
            2
          ],
          [
            3
          ],
          [
            4
          ],
          [
            1,
            2
          ],
          [
            1,
            3
          ]
        ],
        "variable_basis_example": [
          [
            1,
            2
          ],
          [
            1,
            3
          ],
          [
            1,
            4
          ],
          [
            1,
            2,
            3
          ],
          [
            1,
            2,
            4
          ],
          [
            1,
            3,
            4
          ]
        ],
        "family_basis_example": [
          [
            1,
            2,
            3,
            4
          ]
        ]
      },
      {
        "p": 5,
        "k": 1,
        "family_count": 1,
        "answer_basis_size": 0,
        "variable_basis_size": 0,
        "family_basis_size": 0,
        "answer_basis_exact": true,
        "answer_basis_essential": false,
        "variable_basis_exact": true,
        "variable_basis_essential": false,
        "family_basis_exact": true,
        "answer_basis_example": [],
        "variable_basis_example": [],
        "family_basis_example": []
      },
      {
        "p": 5,
        "k": 2,
        "family_count": 1023,
        "answer_basis_size": 15,
        "variable_basis_size": 10,
        "family_basis_size": 1,
        "answer_basis_exact": true,
        "answer_basis_essential": true,
        "variable_basis_exact": true,
        "variable_basis_essential": true,
        "family_basis_exact": true,
        "answer_basis_example": [
          [
            1
          ],
          [
            2
          ],
          [
            3
          ],
          [
            4
          ],
          [
            5
          ],
          [
            1,
            2
          ]
        ],
        "variable_basis_example": [
          [
            1,
            2
          ],
          [
            1,
            3
          ],
          [
            1,
            4
          ],
          [
            1,
            5
          ],
          [
            2,
            3
          ],
          [
            2,
            4
          ]
        ],
        "family_basis_example": [
          [
            1,
            2,
            3,
            4,
            5
          ]
        ]
      },
      {
        "p": 5,
        "k": 3,
        "family_count": 5188,
        "answer_basis_size": 25,
        "variable_basis_size": 20,
        "family_basis_size": 1,
        "answer_basis_exact": true,
        "answer_basis_essential": true,
        "variable_basis_exact": true,
        "variable_basis_essential": true,
        "family_basis_exact": true,
        "answer_basis_example": [
          [
            1
          ],
          [
            2
          ],
          [
            3
          ],
          [
            4
          ],
          [
            5
          ],
          [
            1,
            2
          ]
        ],
        "variable_basis_example": [
          [
            1,
            2
          ],
          [
            1,
            3
          ],
          [
            1,
            4
          ],
          [
            1,
            5
          ],
          [
            2,
            3
          ],
          [
            2,
            4
          ]
        ],
        "family_basis_example": [
          [
            1,
            2,
            3,
            4,
            5
          ]
        ]
      }
    ]
  },
  "semantic_extensions": {
    "counterexample": {
      "extension": "additive_partial_activation",
      "p": 2,
      "k": 2,
      "family": [
        [
          1,
          2
        ]
      ],
      "thresholds": {
        "1,2": 2
      },
      "left_state": [
        0,
        [
          -1,
          -1
        ]
      ],
      "alternate_state": [
        0,
        [
          -1,
          0
        ]
      ],
      "right_state": [
        0,
        [
          0,
          -1
        ]
      ],
      "shared_summary": {
        "depth": 0,
        "completed_variables": []
      },
      "left_output_now": [],
      "alternate_output_now": [],
      "left_output_future": [],
      "alternate_output_future": [
        [
          1,
          2
        ]
      ],
      "break_kind": "coordinate_level_not_hypergraph_specific"
    }
  }
}