{
  "targets": [
    {
      "label": "Q_(3,2)",
      "k": 3,
      "p": 2,
      "canonical_state_count": 54,
      "base_joint_count": 7,
      "base_answer_count": 5,
      "base_witness_count": 7,
      "candidate_action_count": 6,
      "candidate_actions": [
        {
          "representative": [
            1,
            [
              -1,
              -1
            ]
          ],
          "multiplicity": 9
        },
        {
          "representative": [
            2,
            [
              -1,
              -1
            ]
          ],
          "multiplicity": 16
        },
        {
          "representative": [
            3,
            [
              -1,
              -1
            ]
          ],
          "multiplicity": 16
        },
        {
          "representative": [
            3,
            [
              -1,
              3
            ]
          ],
          "multiplicity": 4
        },
        {
          "representative": [
            3,
            [
              3,
              -1
            ]
          ],
          "multiplicity": 4
        },
        {
          "representative": [
            3,
            [
              3,
              3
            ]
          ],
          "multiplicity": 1
        }
      ],
      "exact_frontier": [
        {
          "separator_count": 0,
          "joint_count": 7,
          "answer_count": 5,
          "witness_count": 7,
          "unresolved_pairs": 294,
          "entropy_bits": 2.411751853774935,
          "probe_deficiency_bits": 2.947532580105864,
          "shelf_width_bits": 0.485426827170242
        },
        {
          "separator_count": 1,
          "joint_count": 21,
          "answer_count": 9,
          "witness_count": 21,
          "unresolved_pairs": 98,
          "entropy_bits": 3.9477027792200907,
          "probe_deficiency_bits": 1.3625700793847075,
          "shelf_width_bits": 1.2223924213364485
        },
        {
          "separator_count": 2,
          "joint_count": 38,
          "answer_count": 12,
          "witness_count": 38,
          "unresolved_pairs": 22,
          "entropy_bits": 5.088220835496803,
          "probe_deficiency_bits": 0.506959988719883,
          "shelf_width_bits": 1.6629650127224291
        },
        {
          "separator_count": 3,
          "joint_count": 54,
          "answer_count": 14,
          "witness_count": 54,
          "unresolved_pairs": 0,
          "entropy_bits": 5.7548875021634665,
          "probe_deficiency_bits": 0.0,
          "shelf_width_bits": 1.947532580105864
        },
        {
          "separator_count": 4,
          "joint_count": 54,
          "answer_count": 14,
          "witness_count": 54,
          "unresolved_pairs": 0,
          "entropy_bits": 5.7548875021634665,
          "probe_deficiency_bits": 0.0,
          "shelf_width_bits": 1.947532580105864
        },
        {
          "separator_count": 5,
          "joint_count": 54,
          "answer_count": 14,
          "witness_count": 54,
          "unresolved_pairs": 0,
          "entropy_bits": 5.7548875021634665,
          "probe_deficiency_bits": 0.0,
          "shelf_width_bits": 1.947532580105864
        },
        {
          "separator_count": 6,
          "joint_count": 54,
          "answer_count": 14,
          "witness_count": 54,
          "unresolved_pairs": 0,
          "entropy_bits": 5.7548875021634665,
          "probe_deficiency_bits": 0.0,
          "shelf_width_bits": 1.947532580105864
        }
      ],
      "optimal_subset_masks": [
        7
      ],
      "minimal_basis_size": 3,
      "minimal_basis_representatives": [
        [
          1,
          [
            -1,
            -1
          ]
        ],
        [
          2,
          [
            -1,
            -1
          ]
        ],
        [
          3,
          [
            -1,
            -1
          ]
        ]
      ],
      "greedy_paths": {
        "greedy_joint_gain": [
          [
            3,
            [
              -1,
              -1
            ]
          ],
          [
            2,
            [
              -1,
              -1
            ]
          ],
          [
            1,
            [
              -1,
              -1
            ]
          ]
        ],
        "greedy_pair_gain": [
          [
            2,
            [
              -1,
              -1
            ]
          ],
          [
            3,
            [
              -1,
              -1
            ]
          ],
          [
            1,
            [
              -1,
              -1
            ]
          ]
        ],
        "greedy_info_gain": [
          [
            2,
            [
              -1,
              -1
            ]
          ],
          [
            3,
            [
              -1,
              -1
            ]
          ],
          [
            1,
            [
              -1,
              -1
            ]
          ]
        ]
      },
      "greedy_frontiers": {
        "greedy_joint_gain": [
          {
            "separator_count": 0,
            "joint_count": 7,
            "answer_count": 5,
            "witness_count": 7,
            "unresolved_pairs": 294,
            "entropy_bits": 2.411751853774935,
            "probe_deficiency_bits": 2.947532580105864,
            "shelf_width_bits": 0.485426827170242
          },
          {
            "separator_count": 1,
            "joint_count": 21,
            "answer_count": 9,
            "witness_count": 21,
            "unresolved_pairs": 98,
            "entropy_bits": 3.9477027792200907,
            "probe_deficiency_bits": 1.3625700793847075,
            "shelf_width_bits": 1.2223924213364485
          },
          {
            "separator_count": 2,
            "joint_count": 38,
            "answer_count": 12,
            "witness_count": 38,
            "unresolved_pairs": 22,
            "entropy_bits": 5.088220835496803,
            "probe_deficiency_bits": 0.506959988719883,
            "shelf_width_bits": 1.6629650127224291
          },
          {
            "separator_count": 3,
            "joint_count": 54,
            "answer_count": 14,
            "witness_count": 54,
            "unresolved_pairs": 0,
            "entropy_bits": 5.7548875021634665,
            "probe_deficiency_bits": 0.0,
            "shelf_width_bits": 1.947532580105864
          }
        ],
        "greedy_pair_gain": [
          {
            "separator_count": 0,
            "joint_count": 7,
            "answer_count": 5,
            "witness_count": 7,
            "unresolved_pairs": 294,
            "entropy_bits": 2.411751853774935,
            "probe_deficiency_bits": 2.947532580105864,
            "shelf_width_bits": 0.485426827170242
          },
          {
            "separator_count": 1,
            "joint_count": 18,
            "answer_count": 8,
            "witness_count": 18,
            "unresolved_pairs": 66,
            "entropy_bits": 4.051183798459766,
            "probe_deficiency_bits": 1.584962500721156,
            "shelf_width_bits": 1.1699250014423122
          },
          {
            "separator_count": 2,
            "joint_count": 38,
            "answer_count": 12,
            "witness_count": 38,
            "unresolved_pairs": 22,
            "entropy_bits": 5.088220835496803,
            "probe_deficiency_bits": 0.506959988719883,
            "shelf_width_bits": 1.6629650127224291
          },
          {
            "separator_count": 3,
            "joint_count": 54,
            "answer_count": 14,
            "witness_count": 54,
            "unresolved_pairs": 0,
            "entropy_bits": 5.7548875021634665,
            "probe_deficiency_bits": 0.0,
            "shelf_width_bits": 1.947532580105864
          }
        ],
        "greedy_info_gain": [
          {
            "separator_count": 0,
            "joint_count": 7,
            "answer_count": 5,
            "witness_count": 7,
            "unresolved_pairs": 294,
            "entropy_bits": 2.411751853774935,
            "probe_deficiency_bits": 2.947532580105864,
            "shelf_width_bits": 0.485426827170242
          },
          {
            "separator_count": 1,
            "joint_count": 18,
            "answer_count": 8,
            "witness_count": 18,
            "unresolved_pairs": 66,
            "entropy_bits": 4.051183798459766,
            "probe_deficiency_bits": 1.584962500721156,
            "shelf_width_bits": 1.1699250014423122
          },
          {
            "separator_count": 2,
            "joint_count": 38,
            "answer_count": 12,
            "witness_count": 38,
            "unresolved_pairs": 22,
            "entropy_bits": 5.088220835496803,
            "probe_deficiency_bits": 0.506959988719883,
            "shelf_width_bits": 1.6629650127224291
          },
          {
            "separator_count": 3,
            "joint_count": 54,
            "answer_count": 14,
            "witness_count": 54,
            "unresolved_pairs": 0,
            "entropy_bits": 5.7548875021634665,
            "probe_deficiency_bits": 0.0,
            "shelf_width_bits": 1.947532580105864
          }
        ]
      }
    },
    {
      "label": "Q_(4,2)",
      "k": 4,
      "p": 2,
      "canonical_state_count": 90,
      "base_joint_count": 8,
      "base_answer_count": 6,
      "base_witness_count": 8,
      "candidate_action_count": 7,
      "candidate_actions": [
        {
          "representative": [
            1,
            [
              -1,
              -1
            ]
          ],
          "multiplicity": 9
        },
        {
          "representative": [
            2,
            [
              -1,
              -1
            ]
          ],
          "multiplicity": 16
        },
        {
          "representative": [
            3,
            [
              -1,
              -1
            ]
          ],
          "multiplicity": 25
        },
        {
          "representative": [
            4,
            [
              -1,
              -1
            ]
          ],
          "multiplicity": 25
        },
        {
          "representative": [
            4,
            [
              -1,
              4
            ]
          ],
          "multiplicity": 5
        },
        {
          "representative": [
            4,
            [
              4,
              -1
            ]
          ],
          "multiplicity": 5
        },
        {
          "representative": [
            4,
            [
              4,
              4
            ]
          ],
          "multiplicity": 1
        }
      ],
      "exact_frontier": [
        {
          "separator_count": 0,
          "joint_count": 8,
          "answer_count": 6,
          "witness_count": 8,
          "unresolved_pairs": 782,
          "entropy_bits": 2.5369484802120006,
          "probe_deficiency_bits": 3.4918530963296748,
          "shelf_width_bits": 0.4150374992788439
        },
        {
          "separator_count": 1,
          "joint_count": 25,
          "answer_count": 11,
          "witness_count": 25,
          "unresolved_pairs": 326,
          "entropy_bits": 3.9803075405818102,
          "probe_deficiency_bits": 1.8479969065549504,
          "shelf_width_bits": 1.184424571137427
        },
        {
          "separator_count": 2,
          "joint_count": 47,
          "answer_count": 15,
          "witness_count": 47,
          "unresolved_pairs": 112,
          "entropy_bits": 5.151769484689714,
          "probe_deficiency_bits": 0.9372642446520372,
          "shelf_width_bits": 1.647698256069119
        },
        {
          "separator_count": 3,
          "joint_count": 70,
          "answer_count": 18,
          "witness_count": 70,
          "unresolved_pairs": 26,
          "entropy_bits": 6.002964207440779,
          "probe_deficiency_bits": 0.3625700793847084,
          "shelf_width_bits": 1.9593580155026542
        },
        {
          "separator_count": 4,
          "joint_count": 90,
          "answer_count": 20,
          "witness_count": 90,
          "unresolved_pairs": 0,
          "entropy_bits": 6.491853096329662,
          "probe_deficiency_bits": 0.0,
          "shelf_width_bits": 2.169925001442312
        },
        {
          "separator_count": 5,
          "joint_count": 90,
          "answer_count": 20,
          "witness_count": 90,
          "unresolved_pairs": 0,
          "entropy_bits": 6.491853096329662,
          "probe_deficiency_bits": 0.0,
          "shelf_width_bits": 2.169925001442312
        },
        {
          "separator_count": 6,
          "joint_count": 90,
          "answer_count": 20,
          "witness_count": 90,
          "unresolved_pairs": 0,
          "entropy_bits": 6.491853096329662,
          "probe_deficiency_bits": 0.0,
          "shelf_width_bits": 2.169925001442312
        },
        {
          "separator_count": 7,
          "joint_count": 90,
          "answer_count": 20,
          "witness_count": 90,
          "unresolved_pairs": 0,
          "entropy_bits": 6.491853096329662,
          "probe_deficiency_bits": 0.0,
          "shelf_width_bits": 2.169925001442312
        }
      ],
      "optimal_subset_masks": [
        15
      ],
      "minimal_basis_size": 4,
      "minimal_basis_representatives": [
        [
          1,
          [
            -1,
            -1
          ]
        ],
        [
          2,
          [
            -1,
            -1
          ]
        ],
        [
          3,
          [
            -1,
            -1
          ]
        ],
        [
          4,
          [
            -1,
            -1
          ]
        ]
      ],
      "greedy_paths": {
        "greedy_joint_gain": [
          [
            4,
            [
              -1,
              -1
            ]
          ],
          [
            3,
            [
              -1,
              -1
            ]
          ],
          [
            2,
            [
              -1,
              -1
            ]
          ],
          [
            1,
            [
              -1,
              -1
            ]
          ]
        ],
        "greedy_pair_gain": [
          [
            3,
            [
              -1,
              -1
            ]
          ],
          [
            2,
            [
              -1,
              -1
            ]
          ],
          [
            4,
            [
              -1,
              -1
            ]
          ],
          [
            1,
            [
              -1,
              -1
            ]
          ]
        ],
        "greedy_info_gain": [
          [
            3,
            [
              -1,
              -1
            ]
          ],
          [
            4,
            [
              -1,
              -1
            ]
          ],
          [
            2,
            [
              -1,
              -1
            ]
          ],
          [
            1,
            [
              -1,
              -1
            ]
          ]
        ]
      },
      "greedy_frontiers": {
        "greedy_joint_gain": [
          {
            "separator_count": 0,
            "joint_count": 8,
            "answer_count": 6,
            "witness_count": 8,
            "unresolved_pairs": 782,
            "entropy_bits": 2.5369484802120006,
            "probe_deficiency_bits": 3.4918530963296748,
            "shelf_width_bits": 0.4150374992788439
          },
          {
            "separator_count": 1,
            "joint_count": 25,
            "answer_count": 11,
            "witness_count": 25,
            "unresolved_pairs": 326,
            "entropy_bits": 3.9803075405818102,
            "probe_deficiency_bits": 1.8479969065549504,
            "shelf_width_bits": 1.184424571137427
          },
          {
            "separator_count": 2,
            "joint_count": 47,
            "answer_count": 15,
            "witness_count": 47,
            "unresolved_pairs": 112,
            "entropy_bits": 5.151769484689714,
            "probe_deficiency_bits": 0.9372642446520372,
            "shelf_width_bits": 1.647698256069119
          },
          {
            "separator_count": 3,
            "joint_count": 70,
            "answer_count": 18,
            "witness_count": 70,
            "unresolved_pairs": 26,
            "entropy_bits": 6.002964207440779,
            "probe_deficiency_bits": 0.3625700793847084,
            "shelf_width_bits": 1.9593580155026542
          },
          {
            "separator_count": 4,
            "joint_count": 90,
            "answer_count": 20,
            "witness_count": 90,
            "unresolved_pairs": 0,
            "entropy_bits": 6.491853096329662,
            "probe_deficiency_bits": 0.0,
            "shelf_width_bits": 2.169925001442312
          }
        ],
        "greedy_pair_gain": [
          {
            "separator_count": 0,
            "joint_count": 8,
            "answer_count": 6,
            "witness_count": 8,
            "unresolved_pairs": 782,
            "entropy_bits": 2.5369484802120006,
            "probe_deficiency_bits": 3.4918530963296748,
            "shelf_width_bits": 0.4150374992788439
          },
          {
            "separator_count": 1,
            "joint_count": 22,
            "answer_count": 10,
            "witness_count": 22,
            "unresolved_pairs": 190,
            "entropy_bits": 4.2628805958008265,
            "probe_deficiency_bits": 2.0324214776923775,
            "shelf_width_bits": 1.1375035237499351
          },
          {
            "separator_count": 2,
            "joint_count": 39,
            "answer_count": 13,
            "witness_count": 39,
            "unresolved_pairs": 84,
            "entropy_bits": 5.114075318551896,
            "probe_deficiency_bits": 1.206450877467426,
            "shelf_width_bits": 1.5849625007211565
          },
          {
            "separator_count": 3,
            "joint_count": 70,
            "answer_count": 18,
            "witness_count": 70,
            "unresolved_pairs": 26,
            "entropy_bits": 6.002964207440779,
            "probe_deficiency_bits": 0.3625700793847084,
            "shelf_width_bits": 1.9593580155026542
          },
          {
            "separator_count": 4,
            "joint_count": 90,
            "answer_count": 20,
            "witness_count": 90,
            "unresolved_pairs": 0,
            "entropy_bits": 6.491853096329662,
            "probe_deficiency_bits": 0.0,
            "shelf_width_bits": 2.169925001442312
          }
        ],
        "greedy_info_gain": [
          {
            "separator_count": 0,
            "joint_count": 8,
            "answer_count": 6,
            "witness_count": 8,
            "unresolved_pairs": 782,
            "entropy_bits": 2.5369484802120006,
            "probe_deficiency_bits": 3.4918530963296748,
            "shelf_width_bits": 0.4150374992788439
          },
          {
            "separator_count": 1,
            "joint_count": 22,
            "answer_count": 10,
            "witness_count": 22,
            "unresolved_pairs": 190,
            "entropy_bits": 4.2628805958008265,
            "probe_deficiency_bits": 2.0324214776923775,
            "shelf_width_bits": 1.1375035237499351
          },
          {
            "separator_count": 2,
            "joint_count": 47,
            "answer_count": 15,
            "witness_count": 47,
            "unresolved_pairs": 112,
            "entropy_bits": 5.151769484689714,
            "probe_deficiency_bits": 0.9372642446520372,
            "shelf_width_bits": 1.647698256069119
          },
          {
            "separator_count": 3,
            "joint_count": 70,
            "answer_count": 18,
            "witness_count": 70,
            "unresolved_pairs": 26,
            "entropy_bits": 6.002964207440779,
            "probe_deficiency_bits": 0.3625700793847084,
            "shelf_width_bits": 1.9593580155026542
          },
          {
            "separator_count": 4,
            "joint_count": 90,
            "answer_count": 20,
            "witness_count": 90,
            "unresolved_pairs": 0,
            "entropy_bits": 6.491853096329662,
            "probe_deficiency_bits": 0.0,
            "shelf_width_bits": 2.169925001442312
          }
        ]
      }
    },
    {
      "label": "Q_(5,3)",
      "k": 5,
      "p": 3,
      "canonical_state_count": 783,
      "base_joint_count": 13,
      "base_answer_count": 7,
      "base_witness_count": 13,
      "candidate_action_count": 12,
      "candidate_actions": [
        {
          "representative": [
            1,
            [
              -1,
              -1,
              -1
            ]
          ],
          "multiplicity": 27
        },
        {
          "representative": [
            2,
            [
              -1,
              -1,
              -1
            ]
          ],
          "multiplicity": 64
        },
        {
          "representative": [
            3,
            [
              -1,
              -1,
              -1
            ]
          ],
          "multiplicity": 125
        },
        {
          "representative": [
            4,
            [
              -1,
              -1,
              -1
            ]
          ],
          "multiplicity": 216
        },
        {
          "representative": [
            5,
            [
              -1,
              -1,
              -1
            ]
          ],
          "multiplicity": 216
        },
        {
          "representative": [
            5,
            [
              -1,
              -1,
              5
            ]
          ],
          "multiplicity": 36
        },
        {
          "representative": [
            5,
            [
              -1,
              5,
              -1
            ]
          ],
          "multiplicity": 36
        },
        {
          "representative": [
            5,
            [
              -1,
              5,
              5
            ]
          ],
          "multiplicity": 6
        },
        {
          "representative": [
            5,
            [
              5,
              -1,
              -1
            ]
          ],
          "multiplicity": 36
        },
        {
          "representative": [
            5,
            [
              5,
              -1,
              5
            ]
          ],
          "multiplicity": 6
        },
        {
          "representative": [
            5,
            [
              5,
              5,
              -1
            ]
          ],
          "multiplicity": 6
        },
        {
          "representative": [
            5,
            [
              5,
              5,
              5
            ]
          ],
          "multiplicity": 1
        }
      ],
      "exact_frontier": [
        {
          "separator_count": 0,
          "joint_count": 13,
          "answer_count": 7,
          "witness_count": 13,
          "unresolved_pairs": 58520,
          "entropy_bits": 2.7647233833133353,
          "probe_deficiency_bits": 5.912428779149948,
          "shelf_width_bits": 0.893084796083488
        },
        {
          "separator_count": 1,
          "joint_count": 67,
          "answer_count": 13,
          "witness_count": 67,
          "unresolved_pairs": 21261,
          "entropy_bits": 4.705214702801596,
          "probe_deficiency_bits": 3.546779306833269,
          "shelf_width_bits": 2.36564947231668
        },
        {
          "separator_count": 2,
          "joint_count": 180,
          "answer_count": 18,
          "witness_count": 180,
          "unresolved_pairs": 6745,
          "entropy_bits": 6.429450154171925,
          "probe_deficiency_bits": 2.121015400961366,
          "shelf_width_bits": 3.3219280948873626
        },
        {
          "separator_count": 3,
          "joint_count": 352,
          "answer_count": 22,
          "witness_count": 352,
          "unresolved_pairs": 1792,
          "entropy_bits": 7.87277103490062,
          "probe_deficiency_bits": 1.1534368786537446,
          "shelf_width_bits": 3.999999999999999
        },
        {
          "separator_count": 4,
          "joint_count": 565,
          "answer_count": 25,
          "witness_count": 565,
          "unresolved_pairs": 341,
          "entropy_bits": 8.961527501122426,
          "probe_deficiency_bits": 0.4707614399884914,
          "shelf_width_bits": 4.498250867527825
        },
        {
          "separator_count": 5,
          "joint_count": 783,
          "answer_count": 27,
          "witness_count": 783,
          "unresolved_pairs": 0,
          "entropy_bits": 9.612868497291041,
          "probe_deficiency_bits": 0.0,
          "shelf_width_bits": 4.857980995127573
        },
        {
          "separator_count": 6,
          "joint_count": 783,
          "answer_count": 27,
          "witness_count": 783,
          "unresolved_pairs": 0,
          "entropy_bits": 9.612868497291041,
          "probe_deficiency_bits": 0.0,
          "shelf_width_bits": 4.857980995127573
        },
        {
          "separator_count": 7,
          "joint_count": 783,
          "answer_count": 27,
          "witness_count": 783,
          "unresolved_pairs": 0,
          "entropy_bits": 9.612868497291041,
          "probe_deficiency_bits": 0.0,
          "shelf_width_bits": 4.857980995127573
        },
        {
          "separator_count": 8,
          "joint_count": 783,
          "answer_count": 27,
          "witness_count": 783,
          "unresolved_pairs": 0,
          "entropy_bits": 9.612868497291041,
          "probe_deficiency_bits": 0.0,
          "shelf_width_bits": 4.857980995127573
        },
        {
          "separator_count": 9,
          "joint_count": 783,
          "answer_count": 27,
          "witness_count": 783,
          "unresolved_pairs": 0,
          "entropy_bits": 9.612868497291041,
          "probe_deficiency_bits": 0.0,
          "shelf_width_bits": 4.857980995127573
        },
        {
          "separator_count": 10,
          "joint_count": 783,
          "answer_count": 27,
          "witness_count": 783,
          "unresolved_pairs": 0,
          "entropy_bits": 9.612868497291041,
          "probe_deficiency_bits": 0.0,
          "shelf_width_bits": 4.857980995127573
        },
        {
          "separator_count": 11,
          "joint_count": 783,
          "answer_count": 27,
          "witness_count": 783,
          "unresolved_pairs": 0,
          "entropy_bits": 9.612868497291041,
          "probe_deficiency_bits": 0.0,
          "shelf_width_bits": 4.857980995127573
        },
        {
          "separator_count": 12,
          "joint_count": 783,
          "answer_count": 27,
          "witness_count": 783,
          "unresolved_pairs": 0,
          "entropy_bits": 9.612868497291041,
          "probe_deficiency_bits": 0.0,
          "shelf_width_bits": 4.857980995127573
        }
      ],
      "optimal_subset_masks": [
        31
      ],
      "minimal_basis_size": 5,
      "minimal_basis_representatives": [
        [
          1,
          [
            -1,
            -1,
            -1
          ]
        ],
        [
          2,
          [
            -1,
            -1,
            -1
          ]
        ],
        [
          3,
          [
            -1,
            -1,
            -1
          ]
        ],
        [
          4,
          [
            -1,
            -1,
            -1
          ]
        ],
        [
          5,
          [
            -1,
            -1,
            -1
          ]
        ]
      ],
      "greedy_paths": {
        "greedy_joint_gain": [
          [
            5,
            [
              -1,
              -1,
              -1
            ]
          ],
          [
            4,
            [
              -1,
              -1,
              -1
            ]
          ],
          [
            3,
            [
              -1,
              -1,
              -1
            ]
          ],
          [
            2,
            [
              -1,
              -1,
              -1
            ]
          ],
          [
            1,
            [
              -1,
              -1,
              -1
            ]
          ]
        ],
        "greedy_pair_gain": [
          [
            3,
            [
              -1,
              -1,
              -1
            ]
          ],
          [
            5,
            [
              -1,
              -1,
              -1
            ]
          ],
          [
            2,
            [
              -1,
              -1,
              -1
            ]
          ],
          [
            4,
            [
              -1,
              -1,
              -1
            ]
          ],
          [
            1,
            [
              -1,
              -1,
              -1
            ]
          ]
        ],
        "greedy_info_gain": [
          [
            3,
            [
              -1,
              -1,
              -1
            ]
          ],
          [
            5,
            [
              -1,
              -1,
              -1
            ]
          ],
          [
            2,
            [
              -1,
              -1,
              -1
            ]
          ],
          [
            4,
            [
              -1,
              -1,
              -1
            ]
          ],
          [
            1,
            [
              -1,
              -1,
              -1
            ]
          ]
        ]
      },
      "greedy_frontiers": {
        "greedy_joint_gain": [
          {
            "separator_count": 0,
            "joint_count": 13,
            "answer_count": 7,
            "witness_count": 13,
            "unresolved_pairs": 58520,
            "entropy_bits": 2.7647233833133353,
            "probe_deficiency_bits": 5.912428779149948,
            "shelf_width_bits": 0.893084796083488
          },
          {
            "separator_count": 1,
            "joint_count": 67,
            "answer_count": 13,
            "witness_count": 67,
            "unresolved_pairs": 21261,
            "entropy_bits": 4.705214702801596,
            "probe_deficiency_bits": 3.546779306833269,
            "shelf_width_bits": 2.36564947231668
          },
          {
            "separator_count": 2,
            "joint_count": 180,
            "answer_count": 18,
            "witness_count": 180,
            "unresolved_pairs": 6745,
            "entropy_bits": 6.429450154171925,
            "probe_deficiency_bits": 2.121015400961366,
            "shelf_width_bits": 3.3219280948873626
          },
          {
            "separator_count": 3,
            "joint_count": 352,
            "answer_count": 22,
            "witness_count": 352,
            "unresolved_pairs": 1792,
            "entropy_bits": 7.87277103490062,
            "probe_deficiency_bits": 1.1534368786537446,
            "shelf_width_bits": 3.999999999999999
          },
          {
            "separator_count": 4,
            "joint_count": 565,
            "answer_count": 25,
            "witness_count": 565,
            "unresolved_pairs": 341,
            "entropy_bits": 8.961527501122426,
            "probe_deficiency_bits": 0.4707614399884914,
            "shelf_width_bits": 4.498250867527825
          },
          {
            "separator_count": 5,
            "joint_count": 783,
            "answer_count": 27,
            "witness_count": 783,
            "unresolved_pairs": 0,
            "entropy_bits": 9.612868497291041,
            "probe_deficiency_bits": 0.0,
            "shelf_width_bits": 4.857980995127573
          }
        ],
        "greedy_pair_gain": [
          {
            "separator_count": 0,
            "joint_count": 13,
            "answer_count": 7,
            "witness_count": 13,
            "unresolved_pairs": 58520,
            "entropy_bits": 2.7647233833133353,
            "probe_deficiency_bits": 5.912428779149948,
            "shelf_width_bits": 0.893084796083488
          },
          {
            "separator_count": 1,
            "joint_count": 53,
            "answer_count": 11,
            "witness_count": 53,
            "unresolved_pairs": 7949,
            "entropy_bits": 5.382695123819913,
            "probe_deficiency_bits": 3.884948042727842,
            "shelf_width_bits": 2.2684888359259014
          },
          {
            "separator_count": 2,
            "joint_count": 161,
            "answer_count": 17,
            "witness_count": 161,
            "unresolved_pairs": 3207,
            "entropy_bits": 6.838288276279945,
            "probe_deficiency_bits": 2.281951619176424,
            "shelf_width_bits": 3.2434540368642777
          },
          {
            "separator_count": 3,
            "joint_count": 296,
            "answer_count": 20,
            "witness_count": 296,
            "unresolved_pairs": 1120,
            "entropy_bits": 7.927044742501737,
            "probe_deficiency_bits": 1.4034151316620918,
            "shelf_width_bits": 3.8875252707415866
          },
          {
            "separator_count": 4,
            "joint_count": 565,
            "answer_count": 25,
            "witness_count": 565,
            "unresolved_pairs": 341,
            "entropy_bits": 8.961527501122426,
            "probe_deficiency_bits": 0.4707614399884914,
            "shelf_width_bits": 4.498250867527825
          },
          {
            "separator_count": 5,
            "joint_count": 783,
            "answer_count": 27,
            "witness_count": 783,
            "unresolved_pairs": 0,
            "entropy_bits": 9.612868497291041,
            "probe_deficiency_bits": 0.0,
            "shelf_width_bits": 4.857980995127573
          }
        ],
        "greedy_info_gain": [
          {
            "separator_count": 0,
            "joint_count": 13,
            "answer_count": 7,
            "witness_count": 13,
            "unresolved_pairs": 58520,
            "entropy_bits": 2.7647233833133353,
            "probe_deficiency_bits": 5.912428779149948,
            "shelf_width_bits": 0.893084796083488
          },
          {
            "separator_count": 1,
            "joint_count": 53,
            "answer_count": 11,
            "witness_count": 53,
            "unresolved_pairs": 7949,
            "entropy_bits": 5.382695123819913,
            "probe_deficiency_bits": 3.884948042727842,
            "shelf_width_bits": 2.2684888359259014
          },
          {
            "separator_count": 2,
            "joint_count": 161,
            "answer_count": 17,
            "witness_count": 161,
            "unresolved_pairs": 3207,
            "entropy_bits": 6.838288276279945,
            "probe_deficiency_bits": 2.281951619176424,
            "shelf_width_bits": 3.2434540368642777
          },
          {
            "separator_count": 3,
            "joint_count": 296,
            "answer_count": 20,
            "witness_count": 296,
            "unresolved_pairs": 1120,
            "entropy_bits": 7.927044742501737,
            "probe_deficiency_bits": 1.4034151316620918,
            "shelf_width_bits": 3.8875252707415866
          },
          {
            "separator_count": 4,
            "joint_count": 565,
            "answer_count": 25,
            "witness_count": 565,
            "unresolved_pairs": 341,
            "entropy_bits": 8.961527501122426,
            "probe_deficiency_bits": 0.4707614399884914,
            "shelf_width_bits": 4.498250867527825
          },
          {
            "separator_count": 5,
            "joint_count": 783,
            "answer_count": 27,
            "witness_count": 783,
            "unresolved_pairs": 0,
            "entropy_bits": 9.612868497291041,
            "probe_deficiency_bits": 0.0,
            "shelf_width_bits": 4.857980995127573
          }
        ]
      }
    }
  ],
  "closure_grid": [
    {
      "label": "Q_(1,1)",
      "k": 1,
      "p": 1,
      "canonical_state_count": 5,
      "base_joint_count": 3,
      "candidate_action_count": 2,
      "minimal_basis_size": 1,
      "minimal_basis_representatives": [
        [
          1,
          [
            -1
          ]
        ]
      ]
    },
    {
      "label": "Q_(2,1)",
      "k": 2,
      "p": 1,
      "canonical_state_count": 9,
      "base_joint_count": 4,
      "candidate_action_count": 3,
      "minimal_basis_size": 2,
      "minimal_basis_representatives": [
        [
          1,
          [
            -1
          ]
        ],
        [
          2,
          [
            -1
          ]
        ]
      ]
    },
    {
      "label": "Q_(3,1)",
      "k": 3,
      "p": 1,
      "canonical_state_count": 14,
      "base_joint_count": 5,
      "candidate_action_count": 4,
      "minimal_basis_size": 3,
      "minimal_basis_representatives": [
        [
          1,
          [
            -1
          ]
        ],
        [
          2,
          [
            -1
          ]
        ],
        [
          3,
          [
            -1
          ]
        ]
      ]
    },
    {
      "label": "Q_(4,1)",
      "k": 4,
      "p": 1,
      "canonical_state_count": 20,
      "base_joint_count": 6,
      "candidate_action_count": 5,
      "minimal_basis_size": 4,
      "minimal_basis_representatives": [
        [
          1,
          [
            -1
          ]
        ],
        [
          2,
          [
            -1
          ]
        ],
        [
          3,
          [
            -1
          ]
        ],
        [
          4,
          [
            -1
          ]
        ]
      ]
    },
    {
      "label": "Q_(5,1)",
      "k": 5,
      "p": 1,
      "canonical_state_count": 27,
      "base_joint_count": 7,
      "candidate_action_count": 6,
      "minimal_basis_size": 5,
      "minimal_basis_representatives": [
        [
          1,
          [
            -1
          ]
        ],
        [
          2,
          [
            -1
          ]
        ],
        [
          3,
          [
            -1
          ]
        ],
        [
          4,
          [
            -1
          ]
        ],
        [
          5,
          [
            -1
          ]
        ]
      ]
    },
    {
      "label": "Q_(1,2)",
      "k": 1,
      "p": 2,
      "canonical_state_count": 13,
      "base_joint_count": 5,
      "candidate_action_count": 4,
      "minimal_basis_size": 1,
      "minimal_basis_representatives": [
        [
          1,
          [
            -1,
            -1
          ]
        ]
      ]
    },
    {
      "label": "Q_(2,2)",
      "k": 2,
      "p": 2,
      "canonical_state_count": 29,
      "base_joint_count": 6,
      "candidate_action_count": 5,
      "minimal_basis_size": 2,
      "minimal_basis_representatives": [
        [
          1,
          [
            -1,
            -1
          ]
        ],
        [
          2,
          [
            -1,
            -1
          ]
        ]
      ]
    },
    {
      "label": "Q_(3,2)",
      "k": 3,
      "p": 2,
      "canonical_state_count": 54,
      "base_joint_count": 7,
      "candidate_action_count": 6,
      "minimal_basis_size": 3,
      "minimal_basis_representatives": [
        [
          1,
          [
            -1,
            -1
          ]
        ],
        [
          2,
          [
            -1,
            -1
          ]
        ],
        [
          3,
          [
            -1,
            -1
          ]
        ]
      ]
    },
    {
      "label": "Q_(4,2)",
      "k": 4,
      "p": 2,
      "canonical_state_count": 90,
      "base_joint_count": 8,
      "candidate_action_count": 7,
      "minimal_basis_size": 4,
      "minimal_basis_representatives": [
        [
          1,
          [
            -1,
            -1
          ]
        ],
        [
          2,
          [
            -1,
            -1
          ]
        ],
        [
          3,
          [
            -1,
            -1
          ]
        ],
        [
          4,
          [
            -1,
            -1
          ]
        ]
      ]
    },
    {
      "label": "Q_(5,2)",
      "k": 5,
      "p": 2,
      "canonical_state_count": 139,
      "base_joint_count": 9,
      "candidate_action_count": 8,
      "minimal_basis_size": 5,
      "minimal_basis_representatives": [
        [
          1,
          [
            -1,
            -1
          ]
        ],
        [
          2,
          [
            -1,
            -1
          ]
        ],
        [
          3,
          [
            -1,
            -1
          ]
        ],
        [
          4,
          [
            -1,
            -1
          ]
        ],
        [
          5,
          [
            -1,
            -1
          ]
        ]
      ]
    },
    {
      "label": "Q_(1,3)",
      "k": 1,
      "p": 3,
      "canonical_state_count": 35,
      "base_joint_count": 9,
      "candidate_action_count": 8,
      "minimal_basis_size": 1,
      "minimal_basis_representatives": [
        [
          1,
          [
            -1,
            -1,
            -1
          ]
        ]
      ]
    },
    {
      "label": "Q_(2,3)",
      "k": 2,
      "p": 3,
      "canonical_state_count": 99,
      "base_joint_count": 10,
      "candidate_action_count": 9,
      "minimal_basis_size": 2,
      "minimal_basis_representatives": [
        [
          1,
          [
            -1,
            -1,
            -1
          ]
        ],
        [
          2,
          [
            -1,
            -1,
            -1
          ]
        ]
      ]
    },
    {
      "label": "Q_(3,3)",
      "k": 3,
      "p": 3,
      "canonical_state_count": 224,
      "base_joint_count": 11,
      "candidate_action_count": 10,
      "minimal_basis_size": 3,
      "minimal_basis_representatives": [
        [
          1,
          [
            -1,
            -1,
            -1
          ]
        ],
        [
          2,
          [
            -1,
            -1,
            -1
          ]
        ],
        [
          3,
          [
            -1,
            -1,
            -1
          ]
        ]
      ]
    },
    {
      "label": "Q_(4,3)",
      "k": 4,
      "p": 3,
      "canonical_state_count": 440,
      "base_joint_count": 12,
      "candidate_action_count": 11,
      "minimal_basis_size": 4,
      "minimal_basis_representatives": [
        [
          1,
          [
            -1,
            -1,
            -1
          ]
        ],
        [
          2,
          [
            -1,
            -1,
            -1
          ]
        ],
        [
          3,
          [
            -1,
            -1,
            -1
          ]
        ],
        [
          4,
          [
            -1,
            -1,
            -1
          ]
        ]
      ]
    },
    {
      "label": "Q_(5,3)",
      "k": 5,
      "p": 3,
      "canonical_state_count": 783,
      "base_joint_count": 13,
      "candidate_action_count": 12,
      "minimal_basis_size": 5,
      "minimal_basis_representatives": [
        [
          1,
          [
            -1,
            -1,
            -1
          ]
        ],
        [
          2,
          [
            -1,
            -1,
            -1
          ]
        ],
        [
          3,
          [
            -1,
            -1,
            -1
          ]
        ],
        [
          4,
          [
            -1,
            -1,
            -1
          ]
        ],
        [
          5,
          [
            -1,
            -1,
            -1
          ]
        ]
      ]
    }
  ],
  "stratigraphy": [
    {
      "label": "M_3",
      "algebraic_bits": 3.807354922057604,
      "empirical_bits": 3.807354922057604,
      "probe_joint_bits": 2.321928094887362,
      "probe_witness_bits": 0.0,
      "probe_answer_bits": 2.321928094887362,
      "probe_deficiency_bits": 1.485426827170242,
      "shelf_width_bits": 0.0
    },
    {
      "label": "Q_(3,2)",
      "algebraic_bits": 5.754887502163468,
      "empirical_bits": 5.754887502163468,
      "probe_joint_bits": 2.807354922057604,
      "probe_witness_bits": 2.807354922057604,
      "probe_answer_bits": 2.321928094887362,
      "probe_deficiency_bits": 2.947532580105864,
      "shelf_width_bits": 0.485426827170242
    },
    {
      "label": "Q_(4,2)",
      "algebraic_bits": 6.491853096329675,
      "empirical_bits": 6.491853096329675,
      "probe_joint_bits": 3.0,
      "probe_witness_bits": 3.0,
      "probe_answer_bits": 2.584962500721156,
      "probe_deficiency_bits": 3.4918530963296748,
      "shelf_width_bits": 0.4150374992788439
    },
    {
      "label": "Q_(5,3)",
      "algebraic_bits": 9.612868497291041,
      "empirical_bits": 9.612868497291041,
      "probe_joint_bits": 3.700439718141092,
      "probe_witness_bits": 3.700439718141092,
      "probe_answer_bits": 2.807354922057604,
      "probe_deficiency_bits": 5.912428779149948,
      "shelf_width_bits": 0.893084796083488
    },
    {
      "label": "causal_referee",
      "algebraic_bits": 11.306061689428342,
      "empirical_bits": 3.9068905956085187,
      "probe_joint_bits": 3.9068905956085187,
      "probe_witness_bits": 3.9068905956085187,
      "probe_answer_bits": 2.0,
      "probe_deficiency_bits": 7.399171093819823,
      "shelf_width_bits": 1.9068905956085187
    }
  ]
}